tinydebug/ConsoleReporter.py
tinydebug/Debugger.py
tinydebug/VideoReporter.py
tinydebug/__init__.py
tinydebug/__main__.py
tinydebug/tinydebug.py
tinydebug/util.py
tinydebug/TestSuite/TestSuite.py
tinydebug/TestSuite/__init__.py
tinydebug/TestSuite/binary_search.py
tinydebug/TestSuite/graph_traversal.py
tinydebug/TestSuite/knapsack.py
tinydebug/TestSuite/sorting.py
tinydebug/TestSuite/test_config.json
tinydebug/fonts/SourceCodePro.ttf
tinydebug-0.1.0.dist-info/LICENSE.md
tinydebug-0.1.0.dist-info/METADATA
tinydebug-0.1.0.dist-info/WHEEL
tinydebug-0.1.0.dist-info/entry_points.txt
tinydebug-0.1.0.dist-info/top_level.txt
tinydebug-0.1.0.dist-info/RECORD
