Metadata-Version: 2.1
Name: tinydebug
Version: 0.1.0
Summary: Python Debugger that creates shareable video logs of a program's execution.
Home-page: https://github.com/CCExtractor/AZTinyDebug
Author: Maya Farber Brodsky
Author-email: mayaf2003@gmail.com
License: MIT
Platform: UNKNOWN
Classifier: Programming Language :: Python :: 3
Classifier: License :: OSI Approved :: MIT License
Requires-Dist: Pillow
Requires-Dist: opencv-python
Requires-Dist: numpy
